{
  "source": "soccer",
  "id": 38943,
  "video_id": "e14167cc-3b8b-5969-b0ab-b1f106402e1f",
  "data_type": "online",
  "train_stage": 2,
  "length": 120.0,
  "question_category": "switch_trace",
  "question": [
    {
      "time": 0.0,
      "count": 0,
      "text": "Keep an eye on {Offside}; alert me on occurrence. Answer format: 'Alert - <Event>'."
    },
    {
      "time": 65.498,
      "count": 1,
      "text": "End the previous tracking; from now on continuously track {Ball out of play and Indirect free-kick}. Answer 'Alert - <Event>'."
    }
  ],
  "answer": [
    {
      "start": 81.451,
      "end": 81.451,
      "count": 1,
      "text": "Alert - Ball out of play"
    },
    {
      "start": 118.333,
      "end": 118.333,
      "count": 1,
      "text": "Alert - Indirect free-kick"
    }
  ]
}