{
  "UrlLocal": "england_epl/2015-2016/2016-01-03 - 16-30 Crystal Palace 0 - 3 Chelsea/",
  "UrlYoutube": "",
  "source_file": "england_epl/2015-2016/2016-01-03 - 16-30 Crystal Palace 0 - 3 Chelsea/Labels-v2.json",
  "segment": {
    "start_seconds": 2210,
    "end_seconds": 2250,
    "length_seconds": 40,
    "start_time_mmss": "36:50",
    "end_time_mmss": "37:30",
    "bin_size_seconds": 10,
    "threshold_per_bin": 0.5,
    "mode": "avg"
  },
  "annotations": [
    {
      "gameTime": "1 - 37:01",
      "label": "Ball out of play",
      "position": "2221948",
      "team": "not applicable",
      "visibility": "visible"
    },
    {
      "gameTime": "2 - 37:28",
      "label": "Ball out of play",
      "position": "2248740",
      "team": "not applicable",
      "visibility": "visible"
    }
  ]
}