{
  "UrlLocal": "france_ligue-1/2016-2017/2016-09-16 - 21-45 Caen 0 - 6 Paris SG/",
  "UrlYoutube": "",
  "source_file": "raw_jsons/train_labels/france_ligue-1/2016-2017/2016-09-16 - 21-45 Caen 0 - 6 Paris SG/Labels-v2.json",
  "segment": {
    "start_seconds": 4370,
    "end_seconds": 4490,
    "length_seconds": 120,
    "start_time_mmss": "72:50",
    "end_time_mmss": "74:50",
    "bin_size_seconds": 10,
    "threshold_per_bin": 0.5,
    "mode": "avg"
  },
  "annotations": [
    {
      "gameTime": "2 - 28:19",
      "label": "Foul",
      "position": "1699441",
      "team": "right",
      "visibility": "visible"
    },
    {
      "gameTime": "2 - 28:58",
      "label": "Direct free-kick",
      "position": "1738528",
      "team": "left",
      "visibility": "visible"
    },
    {
      "gameTime": "2 - 29:18",
      "label": "Shots on target",
      "position": "1758945",
      "team": "left",
      "visibility": "visible"
    },
    {
      "gameTime": "2 - 29:20",
      "label": "Shots off target",
      "position": "1760166",
      "team": "left",
      "visibility": "visible"
    },
    {
      "gameTime": "2 - 29:20",
      "label": "Ball out of play",
      "position": "1760614",
      "team": "not applicable",
      "visibility": "visible"
    },
    {
      "gameTime": "2 - 29:45",
      "label": "Shots off target",
      "position": "1785229",
      "team": "right",
      "visibility": "visible"
    }
  ]
}