{
  "source": "soccernet-dense-chain",
  "id": 10214,
  "video_id": "f407a7ab-4de0-51a2-b258-cf68db9c9667",
  "data_type": "online",
  "question_category": "follow_team",
  "question": "At the next {Indirect free-kick}, start tracking that team; notify me on its {Offside}.",
  "answer": [
    {
      "start": 2847.0,
      "end": 2847.0,
      "text": "Trigger: Indirect free-kick by left"
    },
    {
      "start": 2862.0,
      "end": 2862.0,
      "text": "Then: Offside by left"
    }
  ],
  "match_path": "spain_laliga/2015-2016/2015-09-23 - 22-00 Ath Bilbao 1 - 2 Real Madrid/",
  "raw_source_file": "raw_jsons/train_labels/spain_laliga/2015-2016/2015-09-23 - 22-00 Ath Bilbao 1 - 2 Real Madrid/Labels-v2.json",
  "chain_type": "B",
  "trigger_ms": 2847000,
  "team": "left",
  "segment_path": "train/dense_segments/spain_laliga/2015-2016/2015-09-23 - 22-00 Ath Bilbao 1 - 2 Real Madrid/segment_002810_002870.json",
  "segment_meta": {
    "start_seconds": 2810,
    "end_seconds": 2870,
    "length_seconds": 60,
    "start_time_mmss": "46:50",
    "end_time_mmss": "47:50",
    "bin_size_seconds": 10,
    "threshold_per_bin": 0.5,
    "mode": "avg"
  }
}