{
  "source": "soccernet-dense",
  "id": 3088,
  "video_id": "883072b9-d1d4-5dbc-87bc-e3aeab3391fd",
  "data_type": "online",
  "train_stage": 2,
  "length": 40.0,
  "question_category": "Instruction Following",
  "question": "Observe the match footage and tell me whenever {Foul} occurs.",
  "answer": [
    {
      "start": 1607.399,
      "end": 1607.399,
      "text": "Alert: Foul."
    },
    {
      "start": 1615.044,
      "end": 1615.044,
      "text": "Alert: Foul."
    }
  ],
  "segment_path": "dense_single_event_segments/foul/spain_laliga/2016-2017/2016-09-18 - 21-45 Espanyol 0 - 2 Real Madrid/segment_001580_001620.json"
}