{
  "source": "soccernet-dense",
  "id": 4151,
  "video_id": "3e8341de-731b-54aa-82ea-3b45bf10c661",
  "data_type": "online",
  "train_stage": 2,
  "length": 20.0,
  "question_category": "Instruction Following",
  "question": "Watch the video and report when {Foul} happens.",
  "answer": [
    {
      "start": 1967.189,
      "end": 1967.189,
      "text": "Alert: Foul."
    }
  ],
  "segment_path": "train/dense_single_event_segments/foul/italy_serie-a/2016-2017/2017-05-28 - 19-00 AS Roma 3 - 2 Genoa/segment_001950_001970.json"
}