{
  "UrlLocal": "spain_laliga/2014-2015/2015-05-17 - 20-00 Espanyol 1 - 4 Real Madrid/",
  "UrlYoutube": "",
  "source_file": "raw_jsons/train_labels/spain_laliga/2014-2015/2015-05-17 - 20-00 Espanyol 1 - 4 Real Madrid/Labels-v2.json",
  "segment": {
    "start_seconds": 860,
    "end_seconds": 900,
    "length_seconds": 40,
    "start_time_mmss": "14:20",
    "end_time_mmss": "15:00",
    "bin_size_seconds": 10,
    "threshold_per_bin": 1.0,
    "mode": "avg"
  },
  "annotations": [
    {
      "gameTime": "1 - 14:25",
      "label": "Foul",
      "position": "865860",
      "team": "right",
      "visibility": "visible"
    },
    {
      "gameTime": "1 - 14:54",
      "label": "Indirect free-kick",
      "position": "894560",
      "team": "left",
      "visibility": "visible"
    },
    {
      "gameTime": "2 - 14:33",
      "label": "Kick-off",
      "position": "873330",
      "team": "right",
      "visibility": "visible"
    },
    {
      "gameTime": "2 - 14:45",
      "label": "Ball out of play",
      "position": "885532",
      "team": "not applicable",
      "visibility": "visible"
    }
  ]
}