{
  "source": "soccernet-dense",
  "id": 2085,
  "video_id": "870e61a8-600a-58d7-a302-f69bfad17e6b",
  "data_type": "online",
  "train_stage": 2,
  "length": 20.0,
  "question_category": "Instruction Following",
  "question": "Monitor the game stream and alert me upon any {Clearance}.",
  "answer": [
    {
      "start": 2301.225,
      "end": 2301.225,
      "text": "Alert: Clearance."
    }
  ],
  "segment_path": "train/dense_single_event_segments/clearance/england_epl/2016-2017/2017-04-26 - 21-45 Arsenal 1 - 0 Leicester/segment_002290_002310.json"
}