{
  "source": "soccer",
  "id": 33672,
  "video_id": "86ebd62d-767d-51cf-89b7-6ed3af50c221",
  "data_type": "online",
  "train_stage": 2,
  "length": 60.0,
  "question_category": "parallel_question",
  "question": [
    {
      "time": 0.0,
      "count": 0,
      "text": "Keep an eye on {Ball out of play}; ping me every time it happens. Respond 'Alert - <Event>'."
    },
    {
      "time": 33.182,
      "count": 1,
      "text": "Monitor {Foul} and notify me each time it happens. Use: 'Alert - <Event>'."
    }
  ],
  "answer": [
    {
      "start": 33.182,
      "end": 33.182,
      "count": 0,
      "text": "Alert - Ball out of play"
    },
    {
      "start": 59.092,
      "end": 59.092,
      "count": 1,
      "text": "Alert - Foul"
    }
  ]
}