{
  "UrlLocal": "germany_bundesliga/2016-2017/2017-03-17 - 22-30 Dortmund 1 - 0 Ingolstadt/",
  "UrlYoutube": "",
  "source_file": "raw_jsons/train_labels/germany_bundesliga/2016-2017/2017-03-17 - 22-30 Dortmund 1 - 0 Ingolstadt/Labels-v2.json",
  "segment": {
    "start_seconds": 2520,
    "end_seconds": 2540,
    "length_seconds": 20,
    "start_time_mmss": "42:00",
    "end_time_mmss": "42:20",
    "bin_size_seconds": 10,
    "threshold_per_bin": 0.5,
    "mode": "avg"
  },
  "annotations": [
    {
      "gameTime": "2 - 42:17",
      "label": "Shots off target",
      "position": "2537551",
      "team": "left",
      "visibility": "visible"
    }
  ]
}