{
  "source": "soccernet-dense",
  "id": 3093,
  "video_id": "36d69351-50f0-5766-b9cf-7e95e6c90163",
  "data_type": "online",
  "train_stage": 2,
  "length": 20.0,
  "question_category": "Instruction Following",
  "question": "Keep watching the live broadcast and notify me when {Throw-in} happens.",
  "answer": [
    {
      "start": 689.063,
      "end": 689.063,
      "text": "Alert: Throw-in."
    }
  ],
  "segment_path": "train/dense_single_event_segments/throw_in/spain_laliga/2016-2017/2017-02-26 - 18-15 Atl. Madrid 1 - 2 Barcelona/segment_000670_000690.json"
}