{
  "source": "soccer",
  "id": 53271,
  "video_id": "b549ddf3-17cc-5d07-93f0-e00392dd2e1a",
  "data_type": "online",
  "train_stage": 2,
  "length": 120.0,
  "question_category": "parallel_question",
  "question": [
    {
      "time": 0.0,
      "count": 0,
      "text": "Track {Throw-in}; when it occurs, tell me which team (left/right only). Reply: 'Team left/right - <Event>'."
    },
    {
      "time": 85.733,
      "count": 1,
      "text": "Monitor {Clearance} and notify me each time it happens. Use: 'Alert - <Event>'."
    }
  ],
  "answer": [
    {
      "start": 111.039,
      "end": 111.039,
      "count": 0,
      "text": "Team right - Throw-in"
    }
  ]
}