{
  "source": "soccernet-dense",
  "id": 5329,
  "video_id": "ed1434c3-f4dd-5a09-b1be-ee3b07bf6220",
  "data_type": "online",
  "train_stage": 2,
  "length": 20.0,
  "question_category": "Instruction Following",
  "question": "Watch the video and report when {Throw-in} happens.",
  "answer": [
    {
      "start": 2212.787,
      "end": 2212.787,
      "text": "Alert: Throw-in."
    }
  ],
  "segment_path": "train/dense_single_event_segments/throw_in/england_epl/2014-2015/2015-02-21 - 18-00 Crystal Palace 1 - 2 Arsenal/segment_002200_002220.json"
}