{
  "source": "soccer",
  "id": 21076,
  "video_id": "1481a7c3-4842-5cb9-9ba3-490e40cbc02f",
  "data_type": "online",
  "train_stage": 2,
  "length": 60.0,
  "question_category": "count",
  "question": [
    {
      "time": 0.0,
      "count": 0,
      "text": "Watch for {Ball out of play}; on each occurrence, return the cumulative number since question time as an Arabic numeral."
    }
  ],
  "answer": [
    {
      "start": 27.0,
      "end": 27.0,
      "count": 0,
      "text": "1"
    },
    {
      "start": 43.0,
      "end": 43.0,
      "count": 0,
      "text": "2"
    },
    {
      "start": 55.0,
      "end": 55.0,
      "count": 0,
      "text": "3"
    }
  ]
}