{
  "source": "soccernet-dense-chain",
  "id": 23100,
  "video_id": "f9358de9-cf96-591b-8bc4-93628f24fb78",
  "data_type": "online",
  "question_category": "follow_team",
  "question": "At the next {Indirect free-kick}, keep following that team and alert me whenever {Throw-in} happen.",
  "answer": [
    {
      "start": 662.0,
      "end": 662.0,
      "text": "Trigger: Indirect free-kick by right"
    },
    {
      "start": 720.0,
      "end": 720.0,
      "text": "Then: Throw-in by right"
    }
  ],
  "match_path": "england_epl/2014-2015/2015-02-22 - 19-15 Southampton 0 - 2 Liverpool/",
  "raw_source_file": "raw_jsons/train_labels/england_epl/2014-2015/2015-02-22 - 19-15 Southampton 0 - 2 Liverpool/Labels-v2.json",
  "chain_type": "B",
  "trigger_ms": 662000,
  "team": "right",
  "segment_path": "train/dense_segments/england_epl/2014-2015/2015-02-22 - 19-15 Southampton 0 - 2 Liverpool/segment_000630_000730.json",
  "segment_meta": {
    "start_seconds": 630,
    "end_seconds": 730,
    "length_seconds": 100,
    "start_time_mmss": "10:30",
    "end_time_mmss": "12:10",
    "bin_size_seconds": 10,
    "threshold_per_bin": 0.5,
    "mode": "avg"
  }
}