{
  "source": "soccer",
  "id": 32633,
  "video_id": "c35603bd-00f5-5831-9423-b51acb405437",
  "data_type": "online",
  "train_stage": 2,
  "length": 60.0,
  "question_category": "parallel_question",
  "question": [
    {
      "time": 0.0,
      "count": 0,
      "text": "Follow {Throw-in} and respond with the team on occurrence."
    },
    {
      "time": 29.232,
      "count": 1,
      "text": "Please track {Ball out of play} and alert me whenever it occurs."
    }
  ],
  "answer": [
    {
      "start": 40.816,
      "end": 40.816,
      "count": 0,
      "text": "Team right - Throw-in"
    },
    {
      "start": 55.518,
      "end": 55.518,
      "count": 1,
      "text": "Alert - Ball out of play"
    }
  ]
}