{
  "source": "soccernet-dense",
  "id": 3932,
  "video_id": "1ff9352b-4e62-546e-9cb1-f886edb3b577",
  "data_type": "online",
  "train_stage": 2,
  "length": 80.0,
  "question_category": "Instruction Following",
  "question": "Observe the match footage and tell me whenever {Ball out of play} occurs.",
  "answer": [
    {
      "start": 1702.906,
      "end": 1702.906,
      "text": "Alert: Ball out of play."
    },
    {
      "start": 1702.946,
      "end": 1702.946,
      "text": "Alert: Ball out of play."
    },
    {
      "start": 1730.159,
      "end": 1730.159,
      "text": "Alert: Ball out of play."
    },
    {
      "start": 1737.322,
      "end": 1737.322,
      "text": "Alert: Ball out of play."
    }
  ],
  "segment_path": "train/dense_single_event_segments/ball-out-of-play/europe_uefa-champions-league/2016-2017/2016-12-06 - 22-45 Benfica 1 - 2 Napoli/segment_001660_001740.json"
}