{
  "source": "soccer",
  "id": 38100,
  "video_id": "e0681543-ea83-5109-84cb-64ffac1a06fe",
  "data_type": "online",
  "train_stage": 2,
  "length": 120.0,
  "question_category": "switch_trace",
  "question": [
    {
      "time": 0.0,
      "count": 0,
      "text": "Observe {Shots off target and Clearance} and report every time they happen. Exact text 'Alert - <Event>'."
    },
    {
      "time": 48.017,
      "count": 1,
      "text": "End the previous tracking; from now on continuously track {Ball out of play}. Answer 'Alert - <Event>'."
    }
  ],
  "answer": [
    {
      "start": 46.921,
      "end": 46.921,
      "count": 0,
      "text": "Alert - Shots off target"
    },
    {
      "start": 81.162,
      "end": 81.162,
      "count": 1,
      "text": "Alert - Ball out of play"
    },
    {
      "start": 88.868,
      "end": 88.868,
      "count": 1,
      "text": "Alert - Ball out of play"
    },
    {
      "start": 100.747,
      "end": 100.747,
      "count": 1,
      "text": "Alert - Ball out of play"
    }
  ]
}