{
  "source": "soccer",
  "id": 46468,
  "video_id": "9bb1a8c7-20ee-5f6c-a3f5-9a8ed649a089",
  "data_type": "online",
  "train_stage": 2,
  "length": 40.0,
  "question_category": "count",
  "question": [
    {
      "time": 0.0,
      "count": 0,
      "text": "Track {Substitution}. Each time it occurs, output the cumulative count since the question started as a number only (e.g., 3)."
    }
  ],
  "answer": [
    {
      "start": 34.0,
      "end": 34.0,
      "count": 0,
      "text": "1"
    },
    {
      "start": 36.0,
      "end": 36.0,
      "count": 0,
      "text": "2"
    }
  ]
}