{
  "source": "soccernet-dense",
  "id": 3932,
  "video_id": "4d65b9bc-21d4-5066-a37c-c938d3633329",
  "data_type": "online",
  "train_stage": 2,
  "length": 30.0,
  "question_category": "Status Confirmation",
  "question": "Watch the video and monitor {Ball out of play, Clearance, Corner, Direct free-kick, Foul, Goal, Indirect free-kick, Kick-off, Offside, Penalty, Red card, Shots off target, Shots on target, Substitution, Throw-in, Yellow card, Yellow->red card}. Every time one occurs, say which event happened.",
  "answer": [
    {
      "start": 693.625,
      "end": 693.625,
      "text": "Shots off target"
    },
    {
      "start": 695.147,
      "end": 695.147,
      "text": "Ball out of play"
    },
    {
      "start": 705.088,
      "end": 705.088,
      "text": "Foul"
    }
  ],
  "segment_path": "dense_segments/spain_laliga/2015-2016/2016-04-09 - 17-00 Real Madrid 4 - 0 Eibar/segment_000680_000710.json"
}