{
  "source": "soccernet-dense",
  "id": 3704,
  "video_id": "8c98c536-0f9f-577d-b9d1-04385529e26b",
  "data_type": "online",
  "train_stage": 2,
  "length": 40.0,
  "question_category": "Instruction Following",
  "question": "Monitor the game stream and alert me upon any {Throw-in}.",
  "answer": [
    {
      "start": 1775.854,
      "end": 1775.854,
      "text": "Alert: Throw-in."
    },
    {
      "start": 1799.443,
      "end": 1799.443,
      "text": "Alert: Throw-in."
    }
  ],
  "segment_path": "dense_single_event_segments/throw_in/italy_serie-a/2015-2016/2015-09-20 - 13-30 Chievo 0 - 1 Inter/segment_001760_001800.json"
}