{
  "source": "soccernet-dense",
  "id": 125,
  "video_id": "1cac284d-09ec-59f6-8a10-fb2c1de70ccc",
  "data_type": "online",
  "train_stage": 2,
  "length": 20.0,
  "question_category": "Instruction Following",
  "question": "Observe the match footage and tell me whenever {Shots on target} occurs.",
  "answer": [
    {
      "start": 2284.979,
      "end": 2284.979,
      "text": "Alert: Shots on target."
    }
  ],
  "segment_path": "train/dense_single_event_segments/shots-on-target/france_ligue-1/2016-2017/2017-04-30 - 22-00 Nice 3 - 1 Paris SG/segment_002270_002290.json"
}