{
  "source": "soccer",
  "id": 49868,
  "video_id": "956c31db-e065-5270-96f1-976f6529aac4",
  "data_type": "online",
  "train_stage": 2,
  "length": 120.0,
  "question_category": "parallel_question",
  "question": [
    {
      "time": 0.0,
      "count": 0,
      "text": "Observe the stream and alert me for every {Indirect free-kick}."
    },
    {
      "time": 53.632,
      "count": 1,
      "text": "Keep monitoring {Foul}; when it appears, tell me the team."
    }
  ],
  "answer": [
    {
      "start": 31.832,
      "end": 31.832,
      "count": 0,
      "text": "Alert - Indirect free-kick"
    }
  ]
}