{
  "UrlLocal": "england_epl/2015-2016/2016-01-13 - 22-45 Chelsea 2 - 2 West Brom/",
  "UrlYoutube": "",
  "source_file": "raw_jsons/train_labels/england_epl/2015-2016/2016-01-13 - 22-45 Chelsea 2 - 2 West Brom/Labels-v2.json",
  "segment": {
    "start_seconds": 560,
    "end_seconds": 680,
    "length_seconds": 120,
    "start_time_mmss": "09:20",
    "end_time_mmss": "11:20",
    "bin_size_seconds": 10,
    "threshold_per_bin": 1.0,
    "mode": "avg"
  },
  "annotations": [
    {
      "gameTime": "1 - 09:36",
      "label": "Foul",
      "position": "576837",
      "team": "left",
      "visibility": "visible"
    },
    {
      "gameTime": "1 - 09:46",
      "label": "Indirect free-kick",
      "position": "586812",
      "team": "right",
      "visibility": "visible"
    },
    {
      "gameTime": "1 - 10:30",
      "label": "Ball out of play",
      "position": "630206",
      "team": "not applicable",
      "visibility": "visible"
    },
    {
      "gameTime": "1 - 10:47",
      "label": "Throw-in",
      "position": "647464",
      "team": "left",
      "visibility": "visible"
    },
    {
      "gameTime": "1 - 10:49",
      "label": "Ball out of play",
      "position": "649902",
      "team": "not applicable",
      "visibility": "visible"
    },
    {
      "gameTime": "1 - 11:04",
      "label": "Throw-in",
      "position": "664190",
      "team": "left",
      "visibility": "visible"
    },
    {
      "gameTime": "1 - 11:08",
      "label": "Ball out of play",
      "position": "668788",
      "team": "not applicable",
      "visibility": "visible"
    },
    {
      "gameTime": "1 - 11:16",
      "label": "Throw-in",
      "position": "676333",
      "team": "right",
      "visibility": "visible"
    },
    {
      "gameTime": "2 - 09:39",
      "label": "Ball out of play",
      "position": "579725",
      "team": "not applicable",
      "visibility": "visible"
    },
    {
      "gameTime": "2 - 09:59",
      "label": "Throw-in",
      "position": "599972",
      "team": "right",
      "visibility": "visible"
    },
    {
      "gameTime": "2 - 10:28",
      "label": "Shots on target",
      "position": "628723",
      "team": "left",
      "visibility": "visible"
    },
    {
      "gameTime": "2 - 11:12",
      "label": "Ball out of play",
      "position": "672870",
      "team": "not applicable",
      "visibility": "visible"
    }
  ]
}