{
  "source": "soccer",
  "id": 8680,
  "video_id": "d3caa6b5-a482-5157-af3f-2b7e23667481",
  "data_type": "online",
  "train_stage": 2,
  "length": 120.0,
  "question_category": "parallel_question",
  "question": [
    {
      "time": 0.0,
      "count": 0,
      "text": "Monitor {Direct free-kick and Yellow card} and report the team whenever it happens (left/right only). Answer: 'Team left/right - <Event>'."
    },
    {
      "time": 34.111,
      "count": 1,
      "text": "Track {Shots on target} and alert me whenever it happens. Answer: 'Alert - <Event>'."
    }
  ],
  "answer": [
    {
      "start": 34.111,
      "end": 34.111,
      "count": 0,
      "text": "Team right - Yellow card"
    },
    {
      "start": 89.186,
      "end": 89.186,
      "count": 0,
      "text": "Team left - Direct free-kick"
    },
    {
      "start": 93.484,
      "end": 93.484,
      "count": 1,
      "text": "Alert - Shots on target"
    }
  ]
}