{
  "source": "soccer",
  "id": 56993,
  "video_id": "a2920735-2677-5a18-b77c-f12cd1dc97df",
  "data_type": "online",
  "train_stage": 2,
  "length": 120.0,
  "question_category": "parallel_question",
  "question": [
    {
      "time": 0.0,
      "count": 0,
      "text": "Observe the stream and alert me for every {Shots off target}."
    },
    {
      "time": 40.467,
      "count": 1,
      "text": "Monitor {Indirect free-kick}; each time it occurs, tell me the team."
    }
  ],
  "answer": [
    {
      "start": 43.888,
      "end": 43.888,
      "count": 0,
      "text": "Alert - Shots off target"
    },
    {
      "start": 75.941,
      "end": 75.941,
      "count": 1,
      "text": "Team right - Indirect free-kick"
    }
  ]
}