{
  "source": "soccer",
  "id": 20477,
  "video_id": "a5c613b5-f7ca-5f82-9c30-c908c1dab8e4",
  "data_type": "online",
  "train_stage": 2,
  "length": 120.0,
  "question_category": "follow_team",
  "question": [
    {
      "time": 0.0,
      "count": 0,
      "text": "Watch for the next {Shots off target}; then follow that team. Respond 'Trigger: {Shots off target} by left/right', and for {Corner} reply 'Then: <Event> by left/right'."
    }
  ],
  "answer": [
    {
      "start": 69.0,
      "end": 69.0,
      "count": 0,
      "text": "Trigger: Shots off target by right"
    },
    {
      "start": 102.0,
      "end": 102.0,
      "count": 0,
      "text": "Then: Corner by right"
    }
  ]
}