{
  "UrlLocal": "england_epl/2016-2017/2016-11-06 - 19-30 Leicester 1 - 2 West Brom/",
  "UrlYoutube": "",
  "source_file": "england_epl/2016-2017/2016-11-06 - 19-30 Leicester 1 - 2 West Brom/Labels-v2.json",
  "segment": {
    "start_seconds": 1390,
    "end_seconds": 1410,
    "length_seconds": 20,
    "start_time_mmss": "23:10",
    "end_time_mmss": "23:30",
    "bin_size_seconds": 10,
    "threshold_per_bin": 0.5,
    "mode": "avg"
  },
  "annotations": [
    {
      "gameTime": "1 - 23:23",
      "label": "Clearance",
      "position": "1403252",
      "team": "left",
      "visibility": "visible"
    }
  ]
}