{
  "source": "soccer",
  "id": 117659,
  "video_id": "c9643577-545e-5e5d-929a-6e59387eeab8",
  "data_type": "online",
  "train_stage": 2,
  "length": 120.0,
  "question_category": "parallel_question",
  "question": [
    {
      "time": 0.0,
      "count": 0,
      "text": "Monitor {Direct free-kick}; each time it occurs, tell me the team (left/right only). Exact: 'Team left/right - <Event>'."
    },
    {
      "time": 72.19,
      "count": 1,
      "text": "Track {Indirect free-kick} and report which team triggers it (left/right only). Answer 'Team left/right - <Event>'."
    }
  ],
  "answer": [
    {
      "start": 72.19,
      "end": 72.19,
      "count": 0,
      "text": "Team right - Direct free-kick"
    },
    {
      "start": 104.48,
      "end": 104.48,
      "count": 1,
      "text": "Team right - Indirect free-kick"
    }
  ]
}