{
  "UrlLocal": "italy_serie-a/2014-2015/2015-02-15 - 14-30 AC Milan 1 - 1 Empoli/",
  "UrlYoutube": "",
  "source_file": "raw_jsons/train_labels/italy_serie-a/2014-2015/2015-02-15 - 14-30 AC Milan 1 - 1 Empoli/Labels-v2.json",
  "segment": {
    "start_seconds": 1970,
    "end_seconds": 2090,
    "length_seconds": 120,
    "start_time_mmss": "32:50",
    "end_time_mmss": "34:50",
    "bin_size_seconds": 10,
    "threshold_per_bin": 1.0,
    "mode": "avg"
  },
  "annotations": [
    {
      "gameTime": "1 - 33:00",
      "label": "Throw-in",
      "position": "1980516",
      "team": "left",
      "visibility": "visible"
    },
    {
      "gameTime": "1 - 33:29",
      "label": "Ball out of play",
      "position": "2009036",
      "team": "not applicable",
      "visibility": "visible"
    },
    {
      "gameTime": "1 - 33:54",
      "label": "Corner",
      "position": "2034310",
      "team": "right",
      "visibility": "visible"
    },
    {
      "gameTime": "1 - 33:57",
      "label": "Shots off target",
      "position": "2037211",
      "team": "right",
      "visibility": "visible"
    },
    {
      "gameTime": "1 - 34:19",
      "label": "Ball out of play",
      "position": "2059065",
      "team": "not applicable",
      "visibility": "visible"
    },
    {
      "gameTime": "1 - 34:44",
      "label": "Foul",
      "position": "2084569",
      "team": "left",
      "visibility": "visible"
    },
    {
      "gameTime": "2 - 33:35",
      "label": "Shots off target",
      "position": "2015263",
      "team": "left",
      "visibility": "visible"
    },
    {
      "gameTime": "2 - 33:36",
      "label": "Ball out of play",
      "position": "2016424",
      "team": "not applicable",
      "visibility": "visible"
    },
    {
      "gameTime": "2 - 33:57",
      "label": "Substitution",
      "position": "2037247",
      "team": "left",
      "visibility": "visible"
    },
    {
      "gameTime": "2 - 34:27",
      "label": "Ball out of play",
      "position": "2067239",
      "team": "not applicable",
      "visibility": "visible"
    },
    {
      "gameTime": "2 - 34:39",
      "label": "Foul",
      "position": "2079659",
      "team": "right",
      "visibility": "visible"
    },
    {
      "gameTime": "2 - 34:44",
      "label": "Yellow card",
      "position": "2084508",
      "team": "left",
      "visibility": "visible"
    }
  ]
}