{
  "source": "soccer",
  "id": 34409,
  "video_id": "1b09880a-ac1e-5dd5-9186-bb2ce67b767f",
  "data_type": "online",
  "train_stage": 2,
  "length": 60.0,
  "question_category": "parallel_question",
  "question": [
    {
      "time": 0.0,
      "count": 0,
      "text": "Continuously monitor {Offside and Ball out of play} and notify me on occurrence."
    },
    {
      "time": 49.168,
      "count": 1,
      "text": "Continuously monitor {Indirect free-kick} and notify me on occurrence."
    }
  ],
  "answer": [
    {
      "start": 20.782,
      "end": 20.782,
      "count": 0,
      "text": "Alert - Ball out of play"
    },
    {
      "start": 49.168,
      "end": 49.168,
      "count": 0,
      "text": "Alert - Offside"
    },
    {
      "start": 54.891,
      "end": 54.891,
      "count": 1,
      "text": "Alert - Indirect free-kick"
    }
  ]
}