{
  "source": "soccernet-dense",
  "id": 5350,
  "video_id": "68d12e2a-fcf5-5a32-8f4c-455a18c4856b",
  "data_type": "online",
  "train_stage": 2,
  "length": 40.0,
  "question_category": "Instruction Following",
  "question": "Please continuously watch the match video. When {Foul} occurs, alert me.",
  "answer": [
    {
      "start": 2823.227,
      "end": 2823.227,
      "text": "Alert: Foul."
    },
    {
      "start": 2847.37,
      "end": 2847.37,
      "text": "Alert: Foul."
    }
  ],
  "segment_path": "dense_single_event_segments/foul/england_epl/2015-2016/2015-08-08 - 19-30 Chelsea 2 - 2 Swansea/segment_002810_002850.json"
}