{
  "source": "soccernet-dense",
  "id": 1555,
  "video_id": "d53df748-5b71-52ce-99fd-c21aaba2bda2",
  "data_type": "online",
  "train_stage": 2,
  "length": 40.0,
  "question_category": "Instruction Following",
  "question": "Monitor the game stream and alert me upon any {Throw-in}.",
  "answer": [
    {
      "start": 2427.699,
      "end": 2427.699,
      "text": "Alert: Throw-in."
    },
    {
      "start": 2439.081,
      "end": 2439.081,
      "text": "Alert: Throw-in."
    }
  ],
  "segment_path": "dense_single_event_segments/throw_in/europe_uefa-champions-league/2015-2016/2015-09-15 - 21-45 Manchester City 1 - 2 Juventus/segment_002400_002440.json"
}