{
  "source": "soccer",
  "id": 68957,
  "video_id": "ea13eede-54d3-50eb-89cb-f28ad2dfbd77",
  "data_type": "online",
  "train_stage": 2,
  "length": 120.0,
  "question_category": "parallel_question",
  "question": [
    {
      "time": 0.0,
      "count": 0,
      "text": "Keep watching for {Clearance} and let me know each time. Strictly 'Alert - <Event>'."
    },
    {
      "time": 84.492,
      "count": 1,
      "text": "Watch for {Goal} and alert me upon occurrence. Answer format: 'Alert - <Event>'."
    }
  ],
  "answer": [
    {
      "start": 84.492,
      "end": 84.492,
      "count": 0,
      "text": "Alert - Clearance"
    },
    {
      "start": 98.969,
      "end": 98.969,
      "count": 1,
      "text": "Alert - Goal"
    }
  ]
}