{
  "UrlLocal": "england_epl/2015-2016/2016-02-07 - 19-00 Chelsea 1 - 1 Manchester United/",
  "UrlYoutube": "",
  "source_file": "england_epl/2015-2016/2016-02-07 - 19-00 Chelsea 1 - 1 Manchester United/Labels-v2.json",
  "segment": {
    "start_seconds": 1600,
    "end_seconds": 1640,
    "length_seconds": 40,
    "start_time_mmss": "26:40",
    "end_time_mmss": "27:20",
    "bin_size_seconds": 10,
    "threshold_per_bin": 0.5,
    "mode": "avg"
  },
  "annotations": [
    {
      "gameTime": "1 - 27:12",
      "label": "Throw-in",
      "position": "1632316",
      "team": "left",
      "visibility": "visible"
    },
    {
      "gameTime": "2 - 27:09",
      "label": "Throw-in",
      "position": "1629974",
      "team": "left",
      "visibility": "visible"
    }
  ]
}