{
  "UrlLocal": "italy_serie-a/2016-2017/2017-03-19 - 22-45 AS Roma 3 - 1 Sassuolo/",
  "UrlYoutube": "",
  "source_file": "raw_jsons/train_labels/italy_serie-a/2016-2017/2017-03-19 - 22-45 AS Roma 3 - 1 Sassuolo/Labels-v2.json",
  "segment": {
    "start_seconds": 5450,
    "end_seconds": 5570,
    "length_seconds": 120,
    "start_time_mmss": "90:50",
    "end_time_mmss": "92:50",
    "bin_size_seconds": 10,
    "threshold_per_bin": 0.5,
    "mode": "avg"
  },
  "annotations": [
    {
      "gameTime": "2 - 45:58",
      "label": "Ball out of play",
      "position": "2758236",
      "team": "not applicable",
      "visibility": "visible"
    },
    {
      "gameTime": "2 - 46:23",
      "label": "Throw-in",
      "position": "2783215",
      "team": "right",
      "visibility": "visible"
    },
    {
      "gameTime": "2 - 46:32",
      "label": "Offside",
      "position": "2792240",
      "team": "left",
      "visibility": "visible"
    },
    {
      "gameTime": "2 - 46:43",
      "label": "Indirect free-kick",
      "position": "2803110",
      "team": "right",
      "visibility": "visible"
    },
    {
      "gameTime": "2 - 47:07",
      "label": "Foul",
      "position": "2827609",
      "team": "right",
      "visibility": "visible"
    },
    {
      "gameTime": "2 - 47:11",
      "label": "Yellow card",
      "position": "2831204",
      "team": "right",
      "visibility": "visible"
    }
  ]
}