{
  "source": "soccernet-dense",
  "id": 2455,
  "video_id": "c4932948-4031-5933-8d21-ba560af65009",
  "data_type": "online",
  "train_stage": 2,
  "length": 20.0,
  "question_category": "Instruction Following",
  "question": "Monitor the game stream and alert me upon any {Indirect free-kick}.",
  "answer": [
    {
      "start": 1701.665,
      "end": 1701.665,
      "text": "Alert: Indirect free-kick."
    }
  ],
  "segment_path": "dense_single_event_segments/indirect-free_kick/italy_serie-a/2016-2017/2016-12-04 - 14-30 AC Milan 2 - 1 Crotone/segment_001690_001710.json"
}