{
  "source": "soccernet-dense",
  "id": 314,
  "video_id": "bbad4ba6-f4a5-5f30-875f-abf6220f376a",
  "data_type": "online",
  "train_stage": 2,
  "length": 20.0,
  "question_category": "Instruction Following",
  "question": "Monitor the game stream and alert me upon any {Direct free-kick}.",
  "answer": [
    {
      "start": 1834.961,
      "end": 1834.961,
      "text": "Alert: Direct free-kick."
    }
  ],
  "segment_path": "train/dense_single_event_segments/direct-free_kick/germany_bundesliga/2016-2017/2016-12-10 - 17-30 FC Koln 1 - 1 Dortmund/segment_001820_001840.json"
}