{
  "UrlLocal": "england_epl/2015-2016/2015-09-12 - 17-00 Crystal Palace 0 - 1 Manchester City/",
  "UrlYoutube": "",
  "source_file": "raw_jsons/train_labels/england_epl/2015-2016/2015-09-12 - 17-00 Crystal Palace 0 - 1 Manchester City/Labels-v2.json",
  "segment": {
    "start_seconds": 2650,
    "end_seconds": 2730,
    "length_seconds": 80,
    "start_time_mmss": "44:10",
    "end_time_mmss": "45:30",
    "bin_size_seconds": 10,
    "threshold_per_bin": 0.5,
    "mode": "avg"
  },
  "annotations": [
    {
      "gameTime": "1 - 44:28",
      "label": "Ball out of play",
      "position": "2668100",
      "team": "not applicable",
      "visibility": "visible"
    },
    {
      "gameTime": "1 - 44:59",
      "label": "Ball out of play",
      "position": "2699747",
      "team": "not applicable",
      "visibility": "visible"
    },
    {
      "gameTime": "2 - 00:03",
      "label": "Ball out of play",
      "position": "3254",
      "team": "not applicable",
      "visibility": "visible"
    },
    {
      "gameTime": "2 - 00:20",
      "label": "Ball out of play",
      "position": "20340",
      "team": "not applicable",
      "visibility": "visible"
    }
  ]
}