{
  "UrlLocal": "germany_bundesliga/2016-2017/2017-05-13 - 16-30 FC Augsburg 1 - 1 Dortmund/",
  "UrlYoutube": "",
  "source_file": "raw_jsons/train_labels/germany_bundesliga/2016-2017/2017-05-13 - 16-30 FC Augsburg 1 - 1 Dortmund/Labels-v2.json",
  "segment": {
    "start_seconds": 0,
    "end_seconds": 90,
    "length_seconds": 90,
    "start_time_mmss": "00:00",
    "end_time_mmss": "01:30",
    "bin_size_seconds": 10,
    "threshold_per_bin": 1.0,
    "mode": "avg"
  },
  "annotations": [
    {
      "gameTime": "1 - 00:05",
      "label": "Ball out of play",
      "position": "5247",
      "team": "not applicable",
      "visibility": "visible"
    },
    {
      "gameTime": "1 - 00:15",
      "label": "Throw-in",
      "position": "15922",
      "team": "right",
      "visibility": "visible"
    },
    {
      "gameTime": "1 - 00:35",
      "label": "Foul",
      "position": "35858",
      "team": "left",
      "visibility": "visible"
    },
    {
      "gameTime": "2 - 00:21",
      "label": "Ball out of play",
      "position": "21570",
      "team": "not applicable",
      "visibility": "visible"
    },
    {
      "gameTime": "2 - 00:32",
      "label": "Throw-in",
      "position": "32456",
      "team": "right",
      "visibility": "visible"
    },
    {
      "gameTime": "2 - 00:47",
      "label": "Ball out of play",
      "position": "47912",
      "team": "not applicable",
      "visibility": "visible"
    },
    {
      "gameTime": "2 - 00:58",
      "label": "Throw-in",
      "position": "58215",
      "team": "left",
      "visibility": "visible"
    },
    {
      "gameTime": "2 - 01:04",
      "label": "Ball out of play",
      "position": "64475",
      "team": "not applicable",
      "visibility": "visible"
    },
    {
      "gameTime": "2 - 01:21",
      "label": "Throw-in",
      "position": "81830",
      "team": "right",
      "visibility": "visible"
    }
  ]
}