{
  "source": "soccernet-dense",
  "id": 2795,
  "video_id": "443c9076-9fea-5438-a55d-38174d3979aa",
  "data_type": "online",
  "train_stage": 2,
  "length": 20.0,
  "question_category": "Instruction Following",
  "question": "Observe the match footage and tell me whenever {Throw-in} occurs.",
  "answer": [
    {
      "start": 1730.641,
      "end": 1730.641,
      "text": "Alert: Throw-in."
    }
  ],
  "segment_path": "train/dense_single_event_segments/throw_in/spain_laliga/2014-2015/2015-05-17 - 20-00 Espanyol 1 - 4 Real Madrid/segment_001720_001740.json"
}