{
  "source": "soccernet-dense-chain",
  "id": 16044,
  "video_id": "ceb4ec2c-aa9d-5539-8ee4-418cfa41a598",
  "data_type": "online",
  "question_category": "follow_team",
  "question": "Upon the next {Shots on target}, follow the same team and list all subsequent {Throw-in}.",
  "answer": [
    {
      "start": 4590.0,
      "end": 4590.0,
      "text": "Trigger: Shots on target by left"
    },
    {
      "start": 4599.0,
      "end": 4599.0,
      "text": "Then: Throw-in by left"
    }
  ],
  "match_path": "italy_serie-a/2014-2015/2015-04-11 - 21-45 Verona 0 - 3 Inter/",
  "raw_source_file": "raw_jsons/train_labels/italy_serie-a/2014-2015/2015-04-11 - 21-45 Verona 0 - 3 Inter/Labels-v2.json",
  "chain_type": "B",
  "trigger_ms": 4590000,
  "team": "left",
  "segment_path": "train/dense_segments/italy_serie-a/2014-2015/2015-04-11 - 21-45 Verona 0 - 3 Inter/segment_004550_004630.json",
  "segment_meta": {
    "start_seconds": 4550,
    "end_seconds": 4630,
    "length_seconds": 80,
    "start_time_mmss": "75:50",
    "end_time_mmss": "77:10",
    "bin_size_seconds": 10,
    "threshold_per_bin": 0.5,
    "mode": "avg"
  }
}