{
  "source": "soccernet-dense",
  "id": 5762,
  "video_id": "cfaba387-06da-5874-bc92-e77001b75902",
  "data_type": "online",
  "train_stage": 2,
  "length": 20.0,
  "question_category": "Instruction Following",
  "question": "Please continuously watch the match video. When {Foul} occurs, alert me.",
  "answer": [
    {
      "start": 352.878,
      "end": 352.878,
      "text": "Alert: Foul."
    }
  ],
  "segment_path": "dense_single_event_segments/foul/england_epl/2016-2017/2016-11-19 - 18-00 Southampton 0 - 0 Liverpool/segment_000340_000360.json"
}