{
  "source": "soccernet-dense",
  "id": 6982,
  "video_id": "64fd1e63-a077-5217-8a50-ee81cc459ccf",
  "data_type": "online",
  "train_stage": 2,
  "length": 120.0,
  "question_category": "Status Confirmation",
  "question": "Please continuously watch the match video and monitor {Ball out of play, Clearance, Corner, Direct free-kick, Foul, Goal, Indirect free-kick, Kick-off, Offside, Penalty, Red card, Shots off target, Shots on target, Substitution, Throw-in, Yellow card, Yellow->red card}. Whenever a key event occurs, tell me which key event happened?",
  "answer": [
    {
      "start": 9.779,
      "end": 9.779,
      "text": "Ball out of play"
    },
    {
      "start": 19.356,
      "end": 19.356,
      "text": "Throw-in"
    },
    {
      "start": 21.182,
      "end": 21.182,
      "text": "Ball out of play"
    },
    {
      "start": 33.619,
      "end": 33.619,
      "text": "Throw-in"
    },
    {
      "start": 36.622,
      "end": 36.622,
      "text": "Ball out of play"
    },
    {
      "start": 37.143,
      "end": 37.143,
      "text": "Foul"
    },
    {
      "start": 52.96,
      "end": 52.96,
      "text": "Throw-in"
    },
    {
      "start": 59.156,
      "end": 59.156,
      "text": "Ball out of play"
    },
    {
      "start": 72.414,
      "end": 72.414,
      "text": "Indirect free-kick"
    },
    {
      "start": 78.128,
      "end": 78.128,
      "text": "Ball out of play"
    },
    {
      "start": 86.563,
      "end": 86.563,
      "text": "Throw-in"
    },
    {
      "start": 116.128,
      "end": 116.128,
      "text": "Ball out of play"
    }
  ],
  "segment_path": "train/dense_segments/italy_serie-a/2016-2017/2017-03-04 - 17-00 AS Roma 1 - 2 Napoli/segment_000000_000120.json"
}