{
  "source": "soccer",
  "id": 70236,
  "video_id": "490ad900-83a2-5039-a775-feac1b44242c",
  "data_type": "online",
  "train_stage": 2,
  "length": 120.0,
  "question_category": "parallel_question",
  "question": [
    {
      "time": 0.0,
      "count": 0,
      "text": "Observe the stream and alert me for every {Shots off target}."
    },
    {
      "time": 31.172,
      "count": 1,
      "text": "Observe the stream and alert me for every {Foul}."
    }
  ],
  "answer": [
    {
      "start": 48.76,
      "end": 48.76,
      "count": 1,
      "text": "Alert - Foul"
    },
    {
      "start": 87.33,
      "end": 87.33,
      "count": 0,
      "text": "Alert - Shots off target"
    }
  ]
}