{
  "UrlLocal": "germany_bundesliga/2014-2015/2015-05-09 - 16-30 Dortmund 2 - 0 Hertha Berlin/",
  "UrlYoutube": "",
  "source_file": "germany_bundesliga/2014-2015/2015-05-09 - 16-30 Dortmund 2 - 0 Hertha Berlin/Labels-v2.json",
  "segment": {
    "start_seconds": 250,
    "end_seconds": 290,
    "length_seconds": 40,
    "start_time_mmss": "04:10",
    "end_time_mmss": "04:50",
    "bin_size_seconds": 10,
    "threshold_per_bin": 0.5,
    "mode": "avg"
  },
  "annotations": [
    {
      "gameTime": "1 - 04:31",
      "label": "Throw-in",
      "position": "271552",
      "team": "right",
      "visibility": "visible"
    },
    {
      "gameTime": "1 - 04:49",
      "label": "Throw-in",
      "position": "289215",
      "team": "right",
      "visibility": "visible"
    }
  ]
}