{
  "source": "soccernet-dense-chain",
  "id": 22188,
  "video_id": "57ca9e70-81e6-5c49-816d-c3213e8f207b",
  "data_type": "online",
  "question_category": "follow_team",
  "question": "When the next {Direct free-kick} happens, lock onto that team and report every {Foul} it makes.",
  "answer": [
    {
      "start": 1580.0,
      "end": 1580.0,
      "text": "Trigger: Direct free-kick by left"
    },
    {
      "start": 1605.0,
      "end": 1605.0,
      "text": "Then: Foul by left"
    }
  ],
  "match_path": "england_epl/2015-2016/2015-09-12 - 17-00 Crystal Palace 0 - 1 Manchester City/",
  "raw_source_file": "raw_jsons/train_labels/england_epl/2015-2016/2015-09-12 - 17-00 Crystal Palace 0 - 1 Manchester City/Labels-v2.json",
  "chain_type": "B",
  "trigger_ms": 1580000,
  "team": "left",
  "segment_path": "train/dense_segments/england_epl/2015-2016/2015-09-12 - 17-00 Crystal Palace 0 - 1 Manchester City/segment_001570_001650.json",
  "segment_meta": {
    "start_seconds": 1570,
    "end_seconds": 1650,
    "length_seconds": 80,
    "start_time_mmss": "26:10",
    "end_time_mmss": "27:30",
    "bin_size_seconds": 10,
    "threshold_per_bin": 0.5,
    "mode": "avg"
  }
}